pyfibot/GeoIP.dat
pyfibot/__init__.py
pyfibot/botcore.py
pyfibot/colorlogger.py
pyfibot/config_schema.json
pyfibot/pyfibot.py
pyfibot/modules/__init__.py
pyfibot/modules/module_admin.py
pyfibot/modules/module_autoop.py
pyfibot/modules/module_autorejoin.py
pyfibot/modules/module_bmi.py
pyfibot/modules/module_fmi.py
pyfibot/modules/module_geoip.py
pyfibot/modules/module_korona.py
pyfibot/modules/module_matkahuolto.py
pyfibot/modules/module_openweather.py
pyfibot/modules/module_oraakkeli.py
pyfibot/modules/module_posti.py
pyfibot/modules/module_spotify.py
pyfibot/modules/module_tvmaze.py
pyfibot/modules/module_update.py
pyfibot/modules/module_urltitle.py
pyfibot/modules/module_webchat.py
pyfibot/modules/module_wolfram_alpha.py
pyfibot/modules/module_youtube.py
pyfibot/modules/available/module_ask.conf
pyfibot/modules/available/module_ask.py
pyfibot/modules/available/module_autoop_old.py
pyfibot/modules/available/module_expl.py
pyfibot/modules/available/module_forecast.py
pyfibot/modules/available/module_imgur.py
pyfibot/modules/available/module_pgsqlwanha.py
pyfibot/modules/available/module_rss.py
pyfibot/modules/available/module_spotify_noapi.py
pyfibot/modules/available/module_usertrack.py
pyfibot/util/__init__.py
pyfibot/util/dictdiffer.py
pyfibot/util/imgur_auth.py
pyfibot/util/pyfiurl.py
pyfibot/util/twitter_application_auth.py
pyfibot-1.0.1.dist-info/METADATA
pyfibot-1.0.1.dist-info/WHEEL
pyfibot-1.0.1.dist-info/licenses/LICENSE
pyfibot-1.0.1.dist-info/RECORD
